threedi_ws_client/__init__.py
threedi_ws_client/console.py
threedi_ws_client/settings.py
threedi_ws_client/version.py
threedi_ws_client/ws_client.py
threedi_ws_client/commands/__init__.py
threedi_ws_client/commands/active_simulations.py
threedi_ws_client/models/__init__.py
threedi_ws_client/models/monitor.py
threedi_ws_client-0.0.5.dist-info/AUTHORS.rst
threedi_ws_client-0.0.5.dist-info/LICENSE
threedi_ws_client-0.0.5.dist-info/METADATA
threedi_ws_client-0.0.5.dist-info/WHEEL
threedi_ws_client-0.0.5.dist-info/entry_points.txt
threedi_ws_client-0.0.5.dist-info/top_level.txt
threedi_ws_client-0.0.5.dist-info/RECORD
