Metadata-Version: 2.1
Name: threedi-ws-client
Version: 0.0.5
Summary: websocket client for threedi websocket consumer endpoints
Home-page: https://github.com/larsclaussen/threedi-ws-client
Author: Lars Claussen
Author-email: claussen.lars@nelen-schuurmans.nl
License: MIT license
Keywords: threedi_ws_client
Platform: UNKNOWN
Classifier: Development Status :: 2 - Pre-Alpha
Classifier: Intended Audience :: Developers
Classifier: License :: OSI Approved :: MIT License
Classifier: Natural Language :: English
Classifier: Programming Language :: Python :: 3.7
Classifier: Programming Language :: Python :: 3.8
Requires-Python: >=3.7
Requires-Dist: click (==7.1.2)
Requires-Dist: pydantic[dotenv] (==1.4)
Requires-Dist: threedi-api-client (==3.0.17)
Requires-Dist: urllib3 (==1.25.8)
Requires-Dist: websockets (==8.1)
Requires-Dist: rich (==9.4.0)
